refile/__init__.py
refile/cmdline.py
refile/engine.py
refile/printing.py
reFILE-0.4.1.dist-info/DESCRIPTION.rst
reFILE-0.4.1.dist-info/entry_points.txt
reFILE-0.4.1.dist-info/METADATA
reFILE-0.4.1.dist-info/metadata.json
reFILE-0.4.1.dist-info/RECORD
reFILE-0.4.1.dist-info/top_level.txt
reFILE-0.4.1.dist-info/WHEEL
