Metadata-Version: 2.0
Name: reFILE
Version: 0.4.1
Summary: Utility for manipulating files via regex.
Home-page: https://github.com/Sean1708/reFILE
Author: Sean Marshallsay
Author-email: srm.1708@gmail.com
License: UNKNOWN
Download-URL: https://github.com/Sean1708/reFILE.git
Platform: UNKNOWN
Classifier: Development Status :: 3 - Alpha
Classifier: Environment :: Console
Classifier: License :: OSI Approved :: GNU General Public License v3 (GPLv3)
Classifier: Operating System :: Unix
Classifier: Programming Language :: Python
Classifier: Programming Language :: Python :: 2
Classifier: Programming Language :: Python :: 3
Requires-Dist: argparse
Requires-Dist: nose
Requires-Dist: ordereddict
Requires-Dist: pathlib
